EM/__init__.py
EM/em_haplotypes_algo.py
EM/em_mr_algo.py
EM/em_util.py
EM/run_em.py
EM/runfile_em_mt.py
py_graph_em-0.0.3.dist-info/LICENSE
py_graph_em-0.0.3.dist-info/METADATA
py_graph_em-0.0.3.dist-info/WHEEL
py_graph_em-0.0.3.dist-info/top_level.txt
py_graph_em-0.0.3.dist-info/RECORD
