Metadata-Version: 2.1
Name: py-graph-em
Version: 0.0.3
Summary: Graph Based EM
Home-page: https://github.com/nmdp-bioinformatics/py-graph-em
Author: Pradeep Bashyal
Author-email: pbashyal@nmdp.org
License: LGPL 3.0
Keywords: Graph,EM
Platform: UNKNOWN
Classifier: Development Status :: 2 - Pre-Alpha
Classifier: Intended Audience :: Developers
Classifier: License :: OSI Approved :: GNU Lesser General Public License v3 (LGPLv3)
Classifier: Natural Language :: English
Classifier: Programming Language :: Python :: 3.8
Classifier: Programming Language :: Python :: 3.9
Classifier: Programming Language :: Python :: 3.10
Requires-Python: >=3.8
Requires-Dist: toml ==0.10.2
Requires-Dist: py-graph-imputation ==0.0.12
